xmodel/__init__.py
xmodel/_private/__init__.py
xmodel/_private/api/__init__.py
xmodel/_private/api/state.py
xmodel/_private/api/utils.py
xmodel/base/__init__.py
xmodel/base/api.py
xmodel/base/fields.py
xmodel/base/model.py
xmodel/base/structure.py
xmodel/common/__init__.py
xmodel/common/children.py
xmodel/common/lazy.py
xmodel/common/types.py
xmodel/common/unwrap.py
xmodel/common/utils.py
xmodel/converters.py
xmodel/errors.py
xmodel/json.py
xmodel/remote/__init__.py
xmodel/remote/api.py
xmodel/remote/client.py
xmodel/remote/errors.py
xmodel/remote/model.py
xmodel/remote/options.py
xmodel/remote/response_state.py
xmodel/remote/structure.py
xmodel/remote/weak_cache_pool.py
xmodel/util.py
xmodel-1.0.1.dist-info/LICENSE
xmodel-1.0.1.dist-info/METADATA
xmodel-1.0.1.dist-info/WHEEL
xmodel-1.0.1.dist-info/RECORD
