Metadata-Version: 2.1
Name: xmodel
Version: 1.0.1
Summary: Models for working with JSON, ie: JsonModel
Home-page: https://github.com/xyngular/py-xmodel
Author: Josh Orr
Author-email: josh@orr.blue
Requires-Python: >=3.10,<4.0
Classifier: License :: OSI Approved :: The Unlicense (Unlicense)
Classifier: Programming Language :: Python :: 3
Classifier: Programming Language :: Python :: 3.10
Classifier: Programming Language :: Python :: 3.11
Classifier: Programming Language :: Python :: 3.12
Classifier: Topic :: Software Development :: Libraries :: Python Modules
Requires-Dist: ciso8601 (>=2.3.0,<3.0.0)
Requires-Dist: typing-inspect (>=0,<1)
Requires-Dist: xbool (>=1.1.0,<2.0.0)
Requires-Dist: xinject (>=1.4.0,<2.0.0)
Requires-Dist: xloop (>=1.0.1,<2.0.0)
Requires-Dist: xsentinels (>=1.2.1,<2.0.0)
Requires-Dist: xurls (>=1.0.0,<2.0.0)
Project-URL: Repository, https://github.com/xyngular/py-xmodel
